contextq/__init__.py
contextq/main.py
contextq-0.1.4.dist-info/METADATA
contextq-0.1.4.dist-info/WHEEL
contextq-0.1.4.dist-info/entry_points.txt
contextq-0.1.4.dist-info/top_level.txt
contextq-0.1.4.dist-info/RECORD
