Metadata-Version: 2.4
Name: contextq
Version: 0.1.4
Summary: ContextQ: Activation aware LLM Quantization, Make any LLM stick to your tasks
Author: Ayan Jhunjhunwala
Author-email: ayanqwerty@gmail.com
Requires-Dist: torch
Requires-Dist: transformers>=4.51
Requires-Dist: datasets
Requires-Dist: accelerate
Requires-Dist: awq
Dynamic: author
Dynamic: author-email
Dynamic: requires-dist
Dynamic: summary
